validity/Validator.py
validity/ValidityLanguage.py
validity/__init__.py
validity/locale/en.json
validity/locale/ur.json
flask_validity-1.0.0.dist-info/LICENSE
flask_validity-1.0.0.dist-info/METADATA
flask_validity-1.0.0.dist-info/WHEEL
flask_validity-1.0.0.dist-info/top_level.txt
flask_validity-1.0.0.dist-info/RECORD
