Metadata-Version: 2.1
Name: flask-validity
Version: 1.0.0
Summary: The robust validation library for flask
Home-page: https://github.com/alphasofthub/validity
Author: Muhammad Umer Farooq
License: MIT
Project-URL: Bug Tracker, https://github.com/alphasofthub/validity/issues
Platform: any
License-File: LICENSE
Requires-Dist: flask (==2.0.1)
